maestro_reporter-0.4.0.dist-info/licenses/LICENSE
reporter/__init__.py
reporter/__main__.py
reporter/logger.py
reporter/main.py
reporter/models.py
reporter/parser.py
reporter/py.typed
reporter/runner.py
reporter/sender.py
tests/__init__.py
tests/test_functionality.py
tests/test_utils.py
maestro_reporter-0.4.0.dist-info/METADATA
maestro_reporter-0.4.0.dist-info/WHEEL
maestro_reporter-0.4.0.dist-info/entry_points.txt
maestro_reporter-0.4.0.dist-info/top_level.txt
maestro_reporter-0.4.0.dist-info/RECORD
