Metadata-Version: 2.4
Name: maestro-reporter
Version: 0.4.0
Summary: Customized tool to run Maestro tests, parse Maestro report file, and push reports to Lark.
Author: Ryan Febriansyah
Classifier: Programming Language :: Python :: 3
Classifier: Programming Language :: Python :: 3.10
Classifier: Programming Language :: Python :: 3.11
Classifier: Programming Language :: Python :: 3.12
Classifier: License :: OSI Approved :: MIT License
Classifier: Operating System :: OS Independent
Classifier: Topic :: Software Development :: Testing
Requires-Python: >=3.10
License-File: LICENSE
Requires-Dist: requests
Requires-Dist: lxml
Dynamic: license-file
